Workbook

Sheet Sheet1
A1: 交易品种 | B1: 投资组合 | C1: 交易类型 | D1: 审批单号 | E1: 是否预留审批单 | F1: 交易方向 | G1: 对手方 | H1: 交易日 | I1: 交易时间 | J1: 清算速度 | K1: 结算日 | L1: 债券代码 | M1: 券面总额(万) | N1: 券面总额区间下限(万) | O1: 券面总额区间上限(万) | P1: 净价 | Q1: 净价区间下限 | R1: 净价区间上限 | S1: 全价 | T1: 净价 | U1: 行权收益率(%) | V1: 结算金额(元) | W1: 手工维护应计利息 | X1: 应计利息总额(元) | Y1: 应计利息(元) | Z1: 汇率 | AA1: 结算币种 | AB1: 交易方式 | AC1: 清算类型 | AD1: 结算方式 | AE1: 是否行权交易 | AF1: 是否互联互通交易 | AG1: 是否关联方交易 | AH1: 是否有原始交易 | AI1: 策略类型 | AJ1: 策略订单编号 | AK1: 交易所 | AL1: 清算所 | AM1: 托管行 | AN1: 经纪人 | AO1: 税金(元) | AP1: 手续费(元) | AQ1: 佣金(元) | AR1: 备注 | AS1: 占额对象 | AT1: 交易指令 | AU1: 买入方资金账户类型 | AV1: 买入方SWIFT code | AW1: 买入方资金账户账号 | AX1: 买入方资金账户中文户名 | AY1: 买入方资金账户英文户名 | AZ1: 买入方开户行行号 | BA1: 买入方开户行账号 | BB1: 买入方资金账户大额支付系统号 | BC1: 买入方资金开户行中文名 | BD1: 买入方资金开户行英文名 | BE1: 买入方直接参与行行号 | BF1: 买入方直接参与行中文名 | BG1: 买入方直接参与行英文名 | BH1: 买入方间接参与行行号 | BI1: 买入方间接参与行账号 | BJ1: 买入方间接参与行中文名 | BK1: 买入方间接参与行英文名 | BL1: 买入方账户行行号 | BM1: 买入方账户行账号 | BN1: 买入方账户行中文名 | BO1: 买入方账户行英文名 | BP1: 买入方中间行行号 | BQ1: 买入方中间行账号 | BR1: 买入方中间行中文名 | BS1: 买入方中间行英文名 | BT1: 买入方代理行行号 | BU1: 买入方代理行账号 | BV1: 买入方代理行中文名 | BW1: 买入方代理行英文名 | BX1: 卖出方资金账户类型 | BY1: 卖出方SWIFT code | BZ1: 卖出方资金账户账号 | CA1: 卖出方资金账户中文户名 | CB1: 卖出方资金账户英文户名 | CC1: 卖出方开户行行号 | CD1: 卖出方开户行账号 | CE1: 卖出方资金账户大额支付系统号 | CF1: 卖出方资金开户行中文名 | CG1: 卖出方资金开户行英文名 | CH1: 卖出方直接参与行行号 | CI1: 卖出方直接参与行中文名 | CJ1: 卖出方直接参与行英文名 | CK1: 卖出方间接参与行行号 | CL1: 卖出方间接参与行账号 | CM1: 卖出方间接参与行中文名 | CN1: 卖出方间接参与行英文名 | CO1: 卖出方账户行行号 | CP1: 卖出方账户行账号 | CQ1: 卖出方账户行中文名 | CR1: 卖出方账户行英文名 | CS1: 卖出方中间行行号 | CT1: 卖出方中间行账号 | CU1: 卖出方中间行中文名 | CV1: 卖出方中间行英文名 | CW1: 卖出方代理行行号 | CX1: 卖出方代理行账号 | CY1: 卖出方代理行中文名 | CZ1: 卖出方代理行英文名 | DA1: 买入方债券托管账户账号 | DB1: 买入方债券托管账户中文户名 | DC1: 买入方债券托管账户英文户名 | DD1: 买入方债券托管机构 | DE1: 买入方债券托管管理机构 | DF1: 买入方债券托管开户行 | DG1: 买入方债券托管SWIFT code | DH1: 卖出方债券托管账户账号 | DI1: 卖出方债券托管账户中文户名 | DJ1: 卖出方债券托管账户英文户名 | DK1: 卖出方债券托管机构 | DL1: 卖出方债券托管管理机构 | DM1: 卖出方债券托管开户行 | DN1: 卖出方债券托管SWIFT code | DO1: 卖出方债券托管账户账号 | DP1: 卖出方债券托管账户中文户名 | DQ1: 卖出方债券托管账户英文户名 | DR1: 卖出方债券托管机构 | DS1: 卖出方债券托管管理机构 | DT1: 卖出方债券托管开户行 | DU1: 卖出方债券托管SWIFT code
A2: 现券交易 | B2: 债券-201-FVTPL-交易-FIZS | F2: =Sheet2!B2 -> 买入 | G2: =Sheet2!D2 -> 潮州农商银行 | H2: =Sheet2!E2 -> 46163 | J2: =Sheet2!C2 -> T+0 | L2: =Sheet2!F2 -> 260007 | M2: =Sheet2!G2 -> 5000 | T2: =ROUND([1]!b_calc_pv(L2,H2,Sheet2!H2,"1",1),4) -> 100.5263 | AR2: =Sheet2!I2 -> 上家潮州农商银行，下家平安证券、平安银行，履行做市商职责，上下家不偏离。
A3: 现券交易 | B3: 债券-201-FVTPL-交易-FIZS | F3: =Sheet2!B3 -> 卖出 | G3: =Sheet2!D3 -> 平安证券 | H3: =Sheet2!E3 -> 46163 | J3: =Sheet2!C3 -> T+0 | L3: =Sheet2!F3 -> 260007 | M3: =Sheet2!G3 -> 2000 | T3: =ROUND([1]!b_calc_pv(L3,H3,Sheet2!H3,"1",1),4) -> 100.5263 | AR3: =Sheet2!I3 -> 上家潮州农商银行，下家平安证券、平安银行，履行做市商职责，上下家不偏离。
A4: 现券交易 | B4: 债券-201-FVTPL-交易-FIZS | F4: =Sheet2!B4 -> 卖出 | G4: =Sheet2!D4 -> 平安银行 | H4: =Sheet2!E4 -> 46163 | J4: =Sheet2!C4 -> T+0 | L4: =Sheet2!F4 -> 260007 | M4: =Sheet2!G4 -> 3000 | T4: =ROUND([1]!b_calc_pv(L4,H4,Sheet2!H4,"1",1),4) -> 100.5263 | AR4: =Sheet2!I4 -> 上家潮州农商银行，下家平安证券、平安银行，履行做市商职责，上下家不偏离。
A5: 现券交易 | B5: 债券-201-FVTPL-交易-FIZS | F5: =Sheet2!B5 -> 买入 | G5: =Sheet2!D5 -> 启东农商银行 | H5: =Sheet2!E5 -> 46163 | J5: =Sheet2!C5 -> T+0 | L5: =Sheet2!F5 -> 250210 | M5: =Sheet2!G5 -> 5000 | T5: =ROUND([1]!b_calc_pv(L5,H5,Sheet2!H5,"1",1),4) -> 99.9169 | AR5: =Sheet2!I5 -> 上家启东农商银行，下家陕西陇县农商行，履行做市商职责，上下家不偏离。
A6: 现券交易 | B6: 债券-201-FVTPL-交易-FIZS | F6: =Sheet2!B6 -> 卖出 | G6: =Sheet2!D6 -> 陕西陇县农商行 | H6: =Sheet2!E6 -> 46163 | J6: =Sheet2!C6 -> T+0 | L6: =Sheet2!F6 -> 250210 | M6: =Sheet2!G6 -> 5000 | T6: =ROUND([1]!b_calc_pv(L6,H6,Sheet2!H6,"1",1),4) -> 99.9169 | AR6: =Sheet2!I6 -> 上家启东农商银行，下家陕西陇县农商行，履行做市商职责，上下家不偏离。
A7: 现券交易 | B7: 债券-201-FVTPL-交易-FIZS | F7: =Sheet2!B7 -> 买入 | G7: =Sheet2!D7 -> 启东农商银行 | H7: =Sheet2!E7 -> 46163 | J7: =Sheet2!C7 -> T+0 | L7: =Sheet2!F7 -> 250215 | M7: =Sheet2!G7 -> 1000 | T7: =ROUND([1]!b_calc_pv(L7,H7,Sheet2!H7,"1",1),4) -> 98.6295 | AR7: =Sheet2!I7 -> 上家启东农商银行，下家山东滕州农商行，履行做市商职责，上下家不偏离。
A8: 现券交易 | B8: 债券-201-FVTPL-交易-FIZS | F8: =Sheet2!B8 -> 卖出 | G8: =Sheet2!D8 -> 山东滕州农商行 | H8: =Sheet2!E8 -> 46163 | J8: =Sheet2!C8 -> T+0 | L8: =Sheet2!F8 -> 250215 | M8: =Sheet2!G8 -> 1000 | T8: =ROUND([1]!b_calc_pv(L8,H8,Sheet2!H8,"1",1),4) -> 98.6295 | AR8: =Sheet2!I8 -> 上家启东农商银行，下家山东滕州农商行，履行做市商职责，上下家不偏离。
A9: 现券交易 | B9: 债券-201-FVTPL-交易-FIZS | F9: =Sheet2!B9 -> 买入 | G9: =Sheet2!D9 -> 内蒙古农商银行 | H9: =Sheet2!E9 -> 46163 | J9: =Sheet2!C9 -> T+0 | L9: =Sheet2!F9 -> 260002 | M9: =Sheet2!G9 -> 4000 | T9: =ROUND([1]!b_calc_pv(L9,H9,Sheet2!H9,"1",1),4) -> 102.4722 | AR9: =Sheet2!I9 -> 上家内蒙古农商银行，下家平安银行、平安证券，履行做市商职责，上下家不偏离。
A10: 现券交易 | B10: 债券-201-FVTPL-交易-FIZS | F10: =Sheet2!B10 -> 卖出 | G10: =Sheet2!D10 -> 平安银行 | H10: =Sheet2!E10 -> 46163 | J10: =Sheet2!C10 -> T+0 | L10: =Sheet2!F10 -> 260002 | M10: =Sheet2!G10 -> 3000 | T10: =ROUND([1]!b_calc_pv(L10,H10,Sheet2!H10,"1",1),4) -> 102.4722 | AR10: =Sheet2!I10 -> 上家内蒙古农商银行，下家平安银行、平安证券，履行做市商职责，上下家不偏离。
A11: 现券交易 | B11: 债券-201-FVTPL-交易-FIZS | F11: =Sheet2!B11 -> 卖出 | G11: =Sheet2!D11 -> 平安证券 | H11: =Sheet2!E11 -> 46163 | J11: =Sheet2!C11 -> T+0 | L11: =Sheet2!F11 -> 260002 | M11: =Sheet2!G11 -> 1000 | T11: =ROUND([1]!b_calc_pv(L11,H11,Sheet2!H11,"1",1),4) -> 102.4722 | AR11: =Sheet2!I11 -> 上家内蒙古农商银行，下家平安银行、平安证券，履行做市商职责，上下家不偏离。
A12: 现券交易 | B12: 债券-201-FVTPL-交易-FIZS | F12: =Sheet2!B12 -> 买入 | G12: =Sheet2!D12 -> 平安银行 | H12: =Sheet2!E12 -> 46163 | J12: =Sheet2!C12 -> T+0 | L12: =Sheet2!F12 -> 2600002 | M12: =Sheet2!G12 -> 2000 | T12: =ROUND([1]!b_calc_pv(L12,H12,Sheet2!H12,"1",1),4) -> 99.2926 | AR12: =Sheet2!I12 -> 上家平安银行、浙江绍兴瑞丰农商银行，下家杭州银行资管，履行做市商职责，上下家不偏离。
A13: 现券交易 | B13: 债券-201-FVTPL-交易-FIZS | F13: =Sheet2!B13 -> 买入 | G13: =Sheet2!D13 -> 浙江绍兴瑞丰农商银行 | H13: =Sheet2!E13 -> 46163 | J13: =Sheet2!C13 -> T+0 | L13: =Sheet2!F13 -> 2600002 | M13: =Sheet2!G13 -> 1000 | T13: =ROUND([1]!b_calc_pv(L13,H13,Sheet2!H13,"1",1),4) -> 99.2926 | AR13: =Sheet2!I13 -> 上家平安银行、浙江绍兴瑞丰农商银行，下家杭州银行资管，履行做市商职责，上下家不偏离。
... A40: 现券交易 | B40: 债券-201-FVTPL-交易-FIZS | F40: =Sheet2!B40 -> 卖出 | G40: =Sheet2!D40 -> 江西裕民银行 | H40: =Sheet2!E40 -> 46163 | J40: =Sheet2!C40 -> T+0 | L40: =Sheet2!F40 -> 260205 | M40: =Sheet2!G40 -> 1000 | T40: =ROUND([1]!b_calc_pv(L40,H40,Sheet2!H40,"1",1),4) -> 100.9672 | AR40: =Sheet2!I40 -> 上家江苏滨海农商银行，下家申港证券、江西裕民银行，履行做市商职责，上下家不偏离。

Sheet Sheet2
A1: 输入 | B1: 交易方向 | C1: 结算速度 | D1: 对手方 | E1: 交易日 | F1: 债券代码 | G1: 金额 (万) | H1: 收益率 (%) | I1: 备注
A2: 1. 260007 1.578 5000 05.21+0 潮州农商银行 请求 出给 平安证券2k + 平安银行3k | B2: 买入 | C2: T+0 | D2: 潮州农商银行 | E2: 46163 | F2: 260007 | G2: 5000 | H2: 1.578 | I2: 上家潮州农商银行，下家平安证券、平安银行，履行做市商职责，上下家不偏离。
A3: 1. 260007 1.578 5000 05.21+0 潮州农商银行 请求 出给 平安证券2k + 平安银行3k | B3: 卖出 | C3: T+0 | D3: 平安证券 | E3: 46163 | F3: 260007 | G3: 2000 | H3: 1.578 | I3: 上家潮州农商银行，下家平安证券、平安银行，履行做市商职责，上下家不偏离。
A4: 1. 260007 1.578 5000 05.21+0 潮州农商银行 请求 出给 平安证券2k + 平安银行3k | B4: 卖出 | C4: T+0 | D4: 平安银行 | E4: 46163 | F4: 260007 | G4: 3000 | H4: 1.578 | I4: 上家潮州农商银行，下家平安证券、平安银行，履行做市商职责，上下家不偏离。
A5: 2. 250210 1.81 5000 05.21+0 启东农商银行 出给 陕西陇县农商行 请求 | B5: 买入 | C5: T+0 | D5: 启东农商银行 | E5: 46163 | F5: 250210 | G5: 5000 | H5: 1.81 | I5: 上家启东农商银行，下家陕西陇县农商行，履行做市商职责，上下家不偏离。
A6: 2. 250210 1.81 5000 05.21+0 启东农商银行 出给 陕西陇县农商行 请求 | B6: 卖出 | C6: T+0 | D6: 陕西陇县农商行 | E6: 46163 | F6: 250210 | G6: 5000 | H6: 1.81 | I6: 上家启东农商银行，下家陕西陇县农商行，履行做市商职责，上下家不偏离。
A7: 3. 250215 1.815 1000 05.21+0 启东农商银行 出给 山东滕州农商行 请求 | B7: 买入 | C7: T+0 | D7: 启东农商银行 | E7: 46163 | F7: 250215 | G7: 1000 | H7: 1.815 | I7: 上家启东农商银行，下家山东滕州农商行，履行做市商职责，上下家不偏离。
A8: 3. 250215 1.815 1000 05.21+0 启东农商银行 出给 山东滕州农商行 请求 | B8: 卖出 | C8: T+0 | D8: 山东滕州农商行 | E8: 46163 | F8: 250215 | G8: 1000 | H8: 1.815 | I8: 上家启东农商银行，下家山东滕州农商行，履行做市商职责，上下家不偏离。
A9: 1) 29.66Y 260002 2.265 4000 05.21+0 内蒙古农商银行4K 出给 平安银行3K+ 平安证券1K | B9: 买入 | C9: T+0 | D9: 内蒙古农商银行 | E9: 46163 | F9: 260002 | G9: 4000 | H9: 2.265 | I9: 上家内蒙古农商银行，下家平安银行、平安证券，履行做市商职责，上下家不偏离。
A10: 1) 29.66Y 260002 2.265 4000 05.21+0 内蒙古农商银行4K 出给 平安银行3K+ 平安证券1K | B10: 卖出 | C10: T+0 | D10: 平安银行 | E10: 46163 | F10: 260002 | G10: 3000 | H10: 2.265 | I10: 上家内蒙古农商银行，下家平安银行、平安证券，履行做市商职责，上下家不偏离。
A11: 1) 29.66Y 260002 2.265 4000 05.21+0 内蒙古农商银行4K 出给 平安银行3K+ 平安证券1K | B11: 卖出 | C11: T+0 | D11: 平安证券 | E11: 46163 | F11: 260002 | G11: 1000 | H11: 2.265 | I11: 上家内蒙古农商银行，下家平安银行、平安证券，履行做市商职责，上下家不偏离。
A12: 2) 29.93Y 2600002 2.2325 3000 05.21+0 平安银行2K+ 浙江绍兴瑞丰农商银行1K 出给 杭州银行资管3K | B12: 买入 | C12: T+0 | D12: 平安银行 | E12: 46163 | F12: 2600002 | G12: 2000 | H12: 2.2325 | I12: 上家平安银行、浙江绍兴瑞丰农商银行，下家杭州银行资管，履行做市商职责，上下家不偏离。
A13: 2) 29.93Y 2600002 2.2325 3000 05.21+0 平安银行2K+ 浙江绍兴瑞丰农商银行1K 出给 杭州银行资管3K | B13: 买入 | C13: T+0 | D13: 浙江绍兴瑞丰农商银行 | E13: 46163 | F13: 2600002 | G13: 1000 | H13: 2.2325 | I13: 上家平安银行、浙江绍兴瑞丰农商银行，下家杭州银行资管，履行做市商职责，上下家不偏离。
... A40: 5. 260205 1.811 3000 +0 江苏滨海农商银行 请求 出给 申港证券2K+江西裕民银行1K | B40: 卖出 | C40: T+0 | D40: 江西裕民银行 | E40: 46163 | F40: 260205 | G40: 1000 | H40: 1.811 | I40: 上家江苏滨海农商银行，下家申港证券、江西裕民银行，履行做市商职责，上下家不偏离。
